{  "order": "226",  "piece": "227",  "short": "228",  "today": "229",  "true": "230",  "covered": "231",  "cried": "232",  "figure": "233",  "horse": "234",  "money": "235",  "products": "236",  "questions": "237",  "since": "238",  "usually": "239",  "voice": "240",  "able": "241",  "behind": "242",  "carefully": "243",  "common": "244",  "easy": "245",  "fact": "246",  "remember": "247",  "sure": "248",  "vowel": "249",  "whole": "250",  "ago": "251",  "government": "252",  "half": "253",  "machine": "254",  "pair": "255",  "quickly": "256",  "scientist": "257",  "thousand": "258",  "understood": "259",  "wait": "260",  "among": "261",  "building": "262"}